username_checker/__init__.py
username_checker/checker.py
username_checker-0.1.1.dist-info/licenses/LICENSE
username_checker-0.1.1.dist-info/METADATA
username_checker-0.1.1.dist-info/WHEEL
username_checker-0.1.1.dist-info/entry_points.txt
username_checker-0.1.1.dist-info/top_level.txt
username_checker-0.1.1.dist-info/RECORD
