Metadata-Version: 2.4
Name: username-checker
Version: 0.1.1
Summary: Check username availability on popular websites
Author: Muhamadyor
Requires-Python: >=3.6
License-File: LICENSE
Requires-Dist: requests
Requires-Dist: colorama
Dynamic: author
Dynamic: license-file
Dynamic: requires-dist
Dynamic: requires-python
Dynamic: summary
